pyrequire/__about__.py
pyrequire/__init__.py
pyrequire/_helpers.py
pyrequire/_require.py
pyrequire-0.1.0.dist-info/licenses/LICENSE
pyrequire-0.1.0.dist-info/METADATA
pyrequire-0.1.0.dist-info/WHEEL
pyrequire-0.1.0.dist-info/top_level.txt
pyrequire-0.1.0.dist-info/RECORD
