Metadata-Version: 2.4
Name: pyrequire
Version: 0.1.0
Summary: A bunch of decorators for checking specific requirements of Python functions at runtime
Author-email: Keurfon Luu <keurfonluu@outlook.com>
License: BSD 3-Clause License
Project-URL: Homepage, https://github.com/keurfonluu/pyrequire
Project-URL: Code, https://github.com/keurfonluu/pyrequire
Project-URL: Issues, https://github.com/keurfonluu/pyrequire/issues
Keywords: decorators,requirements,utilities
Classifier: License :: OSI Approved :: BSD License
Classifier: Operating System :: OS Independent
Classifier: Development Status :: 4 - Beta
Classifier: Programming Language :: Python :: 3.9
Classifier: Programming Language :: Python :: 3.10
Classifier: Programming Language :: Python :: 3.11
Classifier: Programming Language :: Python :: 3.12
Classifier: Programming Language :: Python :: 3.13
Classifier: Natural Language :: English
Classifier: Intended Audience :: Developers
Classifier: Topic :: Software Development :: Libraries :: Python Modules
Requires-Python: >=3.9
License-File: LICENSE
Dynamic: license-file
